jolteon/__init__.py
jolteon/__main__.py
jolteon/modules.py
jolteon/utils.py
jolteon-0.1.0.dist-info/entry_points.txt
jolteon-0.1.0.dist-info/WHEEL
jolteon-0.1.0.dist-info/METADATA
jolteon-0.1.0.dist-info/RECORD
