Metadata-Version: 2.1
Name: jolteon
Version: 0.1.0
Summary: 
Author: Alex Ceccotti
Author-email: alexceccotti5995@gmail.com
Requires-Python: >=3.10,<4.0
Classifier: Programming Language :: Python :: 3
Classifier: Programming Language :: Python :: 3.10
Classifier: Programming Language :: Python :: 3.11
Requires-Dist: pandas (>=1.5.3,<2.0.0)
Requires-Dist: psycopg2-binary (>=2.9.5,<3.0.0)
Requires-Dist: pydantic[dotenv] (>=1.10.5,<2.0.0)
Requires-Dist: pyyaml (>=6.0,<7.0)
Requires-Dist: tabulate (>=0.9.0,<0.10.0)
Requires-Dist: typer (>=0.7.0,<0.8.0)
